snomed_neo4j_client/__init__.py
snomed_neo4j_client/py.typed
snomed_neo4j_client/snomed_client.py
snomed_neo4j_client-0.1.1.dist-info/METADATA
snomed_neo4j_client-0.1.1.dist-info/WHEEL
snomed_neo4j_client-0.1.1.dist-info/RECORD
