Metadata-Version: 2.4
Name: snomed-neo4j-client
Version: 0.1.1
Summary: A client library for interacting with SNOMED CT data in Neo4j
Project-URL: Homepage, https://github.com/bncszb/snomed-ct-neo4j
Project-URL: Bug Tracker, https://github.com/bncszb/snomed-ct-neo4j/issues
Author-email: Bence Szabó <bszabo96@gmail.com>
License: MIT
Classifier: Development Status :: 4 - Beta
Classifier: Intended Audience :: Healthcare Industry
Classifier: License :: OSI Approved :: MIT License
Classifier: Operating System :: OS Independent
Classifier: Programming Language :: Python :: 3
Classifier: Topic :: Scientific/Engineering :: Medical Science Apps.
Requires-Python: >=3.9
Requires-Dist: snomed-neo4j-core>=0.1.0
